rougek-0.1.5.dist-info/METADATA
rougek-0.1.5.dist-info/WHEEL
rougek-0.1.5.dist-info/entry_points.txt
rougek/__init__.py
rougek/utils/__pycache__/tokenizer.cpython-311.pyc
rougek/utils/__pycache__/stopwords.cpython-311.pyc
rougek/utils/tokenizer.py
rougek/utils/utils.py
rougek/utils/stopwords.py
rougek/__pycache__/__init__.cpython-311.pyc
rougek/cli.py
rougek/evaluation/__init__.py
rougek/evaluation/__pycache__/main.cpython-311.pyc
rougek/evaluation/__pycache__/__init__.cpython-311.pyc
rougek/evaluation/main.py
rougek/evaluation/commands.py
rougek/extract/__init__.py
rougek/extract/utils.py
rougek/extract/commands.py
rougek/_rougek.cpython-311-darwin.so
rougek-0.1.5.dist-info/RECORD
