Metadata-Version: 2.1
Name: rougek
Version: 0.1.5
Classifier: Programming Language :: Rust
Classifier: Programming Language :: Python :: Implementation :: CPython
Classifier: Programming Language :: Python :: Implementation :: PyPy
Requires-Dist: sienna >=0.2.2
Requires-Dist: spacy >=3.5.2
Requires-Dist: click >=8.1.3
Requires-Dist: nltk >=3.8.1
Requires-Python: >=3.8
